Metadata-Version: 2.1
Name: osManag
Version: 0.1.1
Summary: The `osManag`(Operating System Management)library provides a set of utility functions for file and directory management tasks such as creating, removing, renaming, and listing files and directories. It also includes functions for file operations like reading and writing, as well as retrieving system and environmental information.
Home-page: https://github.com/ZOUITANE-Ahmed/osManag.git
Author: Ahmed ZOUITANE
Author-email: zouitane.ahmed02@gmail.com
Classifier: Programming Language :: Python :: 3
Classifier: Programming Language :: Python :: 3.7
Classifier: Programming Language :: Python :: 3.8
Classifier: Programming Language :: Python :: 3.9
Classifier: Programming Language :: Python :: 3.10
Classifier: Programming Language :: Python :: 3.11
Classifier: Programming Language :: Python :: 3.12
Classifier: License :: OSI Approved :: MIT License
Classifier: Operating System :: OS Independent
Requires-Python: >=3.6
License-File: LICENSE
Requires-Dist: colorama>=0.4.4
